inceptalytics/__init__.py
inceptalytics/analytics.py
inceptalytics/utils.py
inceptalytics-0.1.1.dist-info/METADATA
inceptalytics-0.1.1.dist-info/WHEEL
inceptalytics-0.1.1.dist-info/top_level.txt
inceptalytics-0.1.1.dist-info/RECORD
