Metadata-Version: 2.1
Name: inceptalytics
Version: 0.1.1
Summary: INCEpTALYTICS is a package for analysing INCEpTION annotation projects.
Home-page: https://github.com/catalpa-cl/inception-analytics
Author: Marius Hamacher
Author-email: marius.hamacher@outlook.de
Maintainer: Marius Hamacher
Maintainer-email: marius.hamacher@outlook.de
Classifier: Programming Language :: Python :: 3
Classifier: Programming Language :: Python :: 3.8
Requires-Dist: dkpro-cassis
Requires-Dist: pandas
Requires-Dist: scikit-learn
Requires-Dist: krippendorff
Requires-Dist: numpy
Requires-Dist: pygamma-agreement
Requires-Dist: pycaprio (>=0.2.1)
